{
  "Keys": {
    "DiscordToken": "MzEzODYxODEwMzQyMDY4MjI1.DD9Rjg.WZsWpTZPh3kAtOmDpQPqZ8HOu30",
    "TwitchClientId": "3jqbohvo5v4aah7tlkzz37xir7fkls",
    "YouTubeApiKey": "AIzaSyBWNxag6Ilqo-eV_9M8T-7tQvqc72ukFI0",
    "ApiAiKey": "APIAIKEY"
  },
  "BotConfiguration": {
    "CouchBotId": 313861810342068225,
    "Prefix": "!fb",
    "TotalShards": 1
  },
  "Directories": {
    "ConfigRootDirectory": "C:\\programdata\\CouchBot\\",
    "GuildDirectory": "Guilds\\",
    "UserDirectory": "Users\\",
    "LiveDirectory": "Live\\",
    "MixerDirectory": "Mixer\\",
    "PicartoDirectory": "Picarto\\",
    "SmashcastDirectory": "Smashcast\\",
    "TwitchDirectory": "Twitch\\",
    "YouTubeDirectory": "YouTube\\"
  },
  "Platforms": {
    "EnableMixer": true,
    "EnableSmashcast": true,
    "EnableTwitch": true,
    "EnableYouTube": true,
    "EnablePicarto": true,
    "EnableVidMe":  true
  },
  "Intervals": {
    "Picarto": 120,
    "Smashcast": 120,
    "Twitch": 300,
    "TwitchFeed": 300,
    "YouTubePublished": 900,
    "YouTubeLive": 300,
    "VidMe":  900
  }
}